enhanced_mcp/__init__.py
enhanced_mcp/archive_compression.py
enhanced_mcp/asciinema_integration.py
enhanced_mcp/automation_tools.py
enhanced_mcp/base.py
enhanced_mcp/bulk_operations.py
enhanced_mcp/diff_patch.py
enhanced_mcp/file_operations.py
enhanced_mcp/git_integration.py
enhanced_mcp/intelligent_completion.py
enhanced_mcp/mcp_server.py
enhanced_mcp/security_manager.py
enhanced_mcp/sneller_analytics.py
enhanced_mcp/workflow_tools.py
enhanced_mcp_tools-1.0.0.dist-info/METADATA
enhanced_mcp_tools-1.0.0.dist-info/WHEEL
enhanced_mcp_tools-1.0.0.dist-info/entry_points.txt
enhanced_mcp_tools-1.0.0.dist-info/top_level.txt
enhanced_mcp_tools-1.0.0.dist-info/RECORD
