Metadata-Version: 2.4
Name: enhanced-mcp-tools
Version: 1.0.0
Summary: Enhanced MCP tools server with comprehensive development utilities
Author-email: Ryan Malloy <ryan@supported.systems>
License: MIT
Classifier: Development Status :: 3 - Alpha
Classifier: Intended Audience :: Developers
Classifier: Topic :: Software Development
Classifier: Programming Language :: Python :: 3
Classifier: Programming Language :: Python :: 3.10
Classifier: Programming Language :: Python :: 3.11
Classifier: Programming Language :: Python :: 3.12
Classifier: Programming Language :: Python :: 3.13
Requires-Python: >=3.10
Requires-Dist: fastmcp>=2.12.3
Requires-Dist: pillow>=10.0.0
Provides-Extra: enhanced
Requires-Dist: aiofiles>=23.0.0; extra == "enhanced"
Requires-Dist: watchdog>=3.0.0; extra == "enhanced"
Requires-Dist: psutil>=5.9.0; extra == "enhanced"
Requires-Dist: requests>=2.28.0; extra == "enhanced"
Requires-Dist: pillow>=10.0.0; extra == "enhanced"
Provides-Extra: full
Requires-Dist: enhanced-mcp-tools[enhanced]; extra == "full"
Requires-Dist: rich>=13.0.0; extra == "full"
Requires-Dist: pydantic>=2.0.0; extra == "full"
Provides-Extra: dev
Requires-Dist: enhanced-mcp-tools[full]; extra == "dev"
Requires-Dist: pytest>=7.0.0; extra == "dev"
Requires-Dist: pytest-asyncio>=0.21.0; extra == "dev"
Requires-Dist: pytest-cov>=4.0.0; extra == "dev"
Requires-Dist: black>=22.0.0; extra == "dev"
Requires-Dist: ruff>=0.1.0; extra == "dev"
